<?xml version = '1.0' encoding = 'UTF-8'?>
<Diagram class="oracle.dbtools.crest.swingui.relational.DPVRelational" name="Relational_1" id="1CAB1B4A-B81E-2204-89A6-CBAF1B57F87B">
<createdBy>jacek</createdBy>
<modifiedBy>jacek</modifiedBy>
<createdTime>2019-04-04 18:45:02 UTC</createdTime>
<autoRoute>false</autoRoute>
<boxInbox>true</boxInbox>
<showLegend>false</showLegend>
<showLabels>false</showLabels>
<showRelAttributes>false</showRelAttributes>
<gridEnabled>false</gridEnabled>
<showGrid>false</showGrid>
<diagramColor>-1</diagramColor>
<display>false</display>
<notation>1</notation>
<objectViews>
<OView class="oracle.dbtools.crest.swingui.relational.TVTable" oid="060DC114-69A8-ABE2-0AB9-FFBA4C262B38" otype="Table" vid="42959AA8-2B6A-C71F-4958-CA711C14D9E1">
<hideElementsInCurrentOnly>false</hideElementsInCurrentOnly>
<bounds x="1032" y="628" width="166" height="168"/>
</OView>
<OView class="oracle.dbtools.crest.swingui.relational.TVTable" oid="0BA7EEEB-9CB3-8576-0A42-BDD17CCC6D0C" otype="Table" vid="A7FDF7EB-EFCF-1DC4-27D2-AC1DB98109E6">
<hideElementsInCurrentOnly>false</hideElementsInCurrentOnly>
<bounds x="659" y="447" width="121" height="68"/>
</OView>
<OView class="oracle.dbtools.crest.swingui.relational.TVTable" oid="10D91AB7-5600-16A6-F61A-67685AFA121E" otype="Table" vid="A9CBFFC9-0240-75D4-7BC9-0F00E6E23B34">
<hideElementsInCurrentOnly>false</hideElementsInCurrentOnly>
<bounds x="476" y="35" width="198" height="268"/>
</OView>
<OView class="oracle.dbtools.crest.swingui.relational.TVTable" oid="127F1AA8-0ECF-1B9F-A44C-F8B9C3113A92" otype="Table" vid="F68F75EE-A0E5-4733-0815-1E52D112980F">
<hideElementsInCurrentOnly>false</hideElementsInCurrentOnly>
<bounds x="1341" y="464" width="171" height="167"/>
</OView>
<OView class="oracle.dbtools.crest.swingui.relational.TVTable" oid="1C396BFF-F17A-3452-4EED-30DD704F7CDE" otype="Table" vid="9C3FC4CB-3C8A-D042-76E1-44D2387CF24B">
<hideElementsInCurrentOnly>false</hideElementsInCurrentOnly>
<bounds x="360" y="670" width="170" height="110"/>
</OView>
<OView class="oracle.dbtools.crest.swingui.relational.TVTable" oid="33E0AF21-CD28-205B-E445-983F0F85E9A6" otype="Table" vid="3172480C-A348-D4F2-8F10-7057E32E7A56">
<hideElementsInCurrentOnly>false</hideElementsInCurrentOnly>
<bounds x="833" y="447" width="110" height="70"/>
</OView>
<OView class="oracle.dbtools.crest.swingui.relational.TVTable" oid="3487320F-2F38-288A-C2A7-2B2E3C43A114" otype="Table" vid="EFE05A7C-ADB9-56D5-F564-F70226A17BDF">
<hideElementsInCurrentOnly>false</hideElementsInCurrentOnly>
<bounds x="989" y="417" width="252" height="145"/>
</OView>
<OView class="oracle.dbtools.crest.swingui.relational.TVTable" oid="368763E5-D1F0-DD7C-EFBB-1DEB3C24B451" otype="Table" vid="6A8A6E22-9773-23A6-1916-3218F9338106">
<hideElementsInCurrentOnly>false</hideElementsInCurrentOnly>
<bounds x="918" y="246" width="132" height="78"/>
</OView>
<OView class="oracle.dbtools.crest.swingui.relational.TVTable" oid="51DA6E58-85FF-850B-7B57-247A39C6B956" otype="Table" vid="F8FE3B5D-08E0-92C7-421B-786245FFC5FE">
<hideElementsInCurrentOnly>false</hideElementsInCurrentOnly>
<bounds x="1032" y="182" width="106" height="54"/>
</OView>
<OView class="oracle.dbtools.crest.swingui.relational.TVTable" oid="5BDB754A-4DB5-6A39-817F-35A36B1E53B7" otype="Table" vid="21ABDA96-964C-DA8F-4138-A251F1133B96">
<hideElementsInCurrentOnly>false</hideElementsInCurrentOnly>
<bounds x="390" y="730" width="170" height="110"/>
</OView>
<OView class="oracle.dbtools.crest.swingui.relational.TVTable" oid="661D95A4-9C44-3707-F51B-E9F3495097BC" otype="Table" vid="892DB848-0A51-1A36-7F03-155332A3F8BD">
<hideElementsInCurrentOnly>false</hideElementsInCurrentOnly>
<bounds x="354" y="635" width="192" height="138"/>
</OView>
<OView class="oracle.dbtools.crest.swingui.relational.TVTable" oid="9FD57899-C508-C78D-F366-CC7940147475" otype="Table" vid="4CBEBAE7-ED66-6E75-0B48-30AAC1BB68E3">
<hideElementsInCurrentOnly>false</hideElementsInCurrentOnly>
<bounds x="514" y="449" width="99" height="73"/>
</OView>
<OView class="oracle.dbtools.crest.swingui.relational.TVTable" oid="AAE1580B-F9AE-480A-6947-A01F0B11D00F" otype="Table" vid="A442EABB-80E2-5116-2221-8665ECDEE1BD">
<hideElementsInCurrentOnly>false</hideElementsInCurrentOnly>
<bounds x="606" y="598" width="100" height="67"/>
</OView>
<OView class="oracle.dbtools.crest.swingui.relational.TVTable" oid="AD4AB3B1-183B-EB51-0AC2-2112400D9F2E" otype="Table" vid="DB89BD44-4B50-A471-EB20-6339C2F1F1CE">
<hideElementsInCurrentOnly>false</hideElementsInCurrentOnly>
<bounds x="91" y="46" width="220" height="335"/>
</OView>
<OView class="oracle.dbtools.crest.swingui.relational.TVTable" oid="AFED49FA-0F06-F549-4B01-1392DC125264" otype="Table" vid="5618833E-802B-EC56-5D2B-AF0655C7D81C">
<hideElementsInCurrentOnly>false</hideElementsInCurrentOnly>
<bounds x="774" y="84" width="170" height="110"/>
</OView>
<OView class="oracle.dbtools.crest.swingui.relational.TVTable" oid="B1315D40-B2E5-6908-7768-C41D92F44AFA" otype="Table" vid="9DF2C5AC-063F-65C1-98FC-44C4C5568FF9">
<hideElementsInCurrentOnly>false</hideElementsInCurrentOnly>
<bounds x="1029" y="102" width="94" height="47"/>
</OView>
<OView class="oracle.dbtools.crest.swingui.relational.TVTable" oid="B9063978-8A1E-94DC-5D77-DE4BC54BAFF8" otype="Table" vid="1C62262E-F54D-DD69-680A-4D768CCFDAD4">
<hideElementsInCurrentOnly>false</hideElementsInCurrentOnly>
<bounds x="320" y="590" width="170" height="110"/>
</OView>
</objectViews>
<connectors>
<Connector class="oracle.dbtools.crest.swingui.relational.TVFKRelation" oid="15752F6B-E6BA-7132-E189-1C12E4423641" otype="FKIndexAssociation" vid_source="9DF2C5AC-063F-65C1-98FC-44C4C5568FF9" vid_target="F8FE3B5D-08E0-92C7-421B-786245FFC5FE">
<hideElementsInCurrentOnly>false</hideElementsInCurrentOnly>
<backgroundColor>-16777216</backgroundColor>
<lineWidth>1</lineWidth>
<points>
<point x="1077" y="149"/>
<point x="1077" y="182"/>
</points>
</Connector>
<Connector class="oracle.dbtools.crest.swingui.relational.TVFKRelation" oid="1904402F-F641-5C37-C188-70D89D8B6445" otype="FKIndexAssociation" vid_source="6A8A6E22-9773-23A6-1916-3218F9338106" vid_target="21ABDA96-964C-DA8F-4138-A251F1133B96">
<hideElementsInCurrentOnly>false</hideElementsInCurrentOnly>
<backgroundColor>-16777216</backgroundColor>
<lineWidth>1</lineWidth>
<points>
<point x="944" y="324"/>
<point x="530" y="730"/>
</points>
</Connector>
<Connector class="oracle.dbtools.crest.swingui.relational.TVFKRelation" oid="1F87365E-616D-A55E-00E6-3DD66C053E49" otype="FKIndexAssociation" vid_source="EFE05A7C-ADB9-56D5-F564-F70226A17BDF" vid_target="21ABDA96-964C-DA8F-4138-A251F1133B96">
<hideElementsInCurrentOnly>false</hideElementsInCurrentOnly>
<backgroundColor>-16777216</backgroundColor>
<lineWidth>1</lineWidth>
<points>
<point x="989" y="547"/>
<point x="560" y="745"/>
</points>
</Connector>
<Connector class="oracle.dbtools.crest.swingui.relational.TVFKRelation" oid="29723A87-6A9A-B984-3EA8-C4940F3DD067" otype="FKIndexAssociation" vid_source="F8FE3B5D-08E0-92C7-421B-786245FFC5FE" vid_target="1C62262E-F54D-DD69-680A-4D768CCFDAD4">
<hideElementsInCurrentOnly>false</hideElementsInCurrentOnly>
<backgroundColor>-16777216</backgroundColor>
<lineWidth>1</lineWidth>
<points>
<point x="1042" y="236"/>
<point x="490" y="590"/>
</points>
</Connector>
<Connector class="oracle.dbtools.crest.swingui.relational.TVFKRelation" oid="29984F42-D77F-2B81-11EC-904059848577" otype="FKIndexAssociation" vid_source="42959AA8-2B6A-C71F-4958-CA711C14D9E1" vid_target="892DB848-0A51-1A36-7F03-155332A3F8BD">
<hideElementsInCurrentOnly>false</hideElementsInCurrentOnly>
<backgroundColor>-16777216</backgroundColor>
<lineWidth>1</lineWidth>
<points>
<point x="1032" y="704"/>
<point x="546" y="704"/>
</points>
</Connector>
<Connector class="oracle.dbtools.crest.swingui.relational.TVFKRelation" oid="3884B4AC-5978-9551-0085-7AF6FD09E193" otype="FKIndexAssociation" vid_source="4CBEBAE7-ED66-6E75-0B48-30AAC1BB68E3" vid_target="A9CBFFC9-0240-75D4-7BC9-0F00E6E23B34">
<hideElementsInCurrentOnly>false</hideElementsInCurrentOnly>
<backgroundColor>-16777216</backgroundColor>
<lineWidth>1</lineWidth>
<points>
<point x="578" y="449"/>
<point x="578" y="303"/>
</points>
</Connector>
<Connector class="oracle.dbtools.crest.swingui.relational.TVFKRelation" oid="406C033A-BF55-4687-BF99-E209384315EC" otype="FKIndexAssociation" vid_source="4CBEBAE7-ED66-6E75-0B48-30AAC1BB68E3" vid_target="A7FDF7EB-EFCF-1DC4-27D2-AC1DB98109E6">
<hideElementsInCurrentOnly>false</hideElementsInCurrentOnly>
<backgroundColor>-16777216</backgroundColor>
<lineWidth>1</lineWidth>
<points>
<point x="613" y="482"/>
<point x="659" y="482"/>
</points>
</Connector>
<Connector class="oracle.dbtools.crest.swingui.relational.TVFKRelation" oid="4848EAF4-4AB5-035F-EC36-B6F7B7FBA24E" otype="FKIndexAssociation" vid_source="A9CBFFC9-0240-75D4-7BC9-0F00E6E23B34" vid_target="DB89BD44-4B50-A471-EB20-6339C2F1F1CE">
<hideElementsInCurrentOnly>false</hideElementsInCurrentOnly>
<backgroundColor>-16777216</backgroundColor>
<lineWidth>1</lineWidth>
<points>
<point x="476" y="174"/>
<point x="311" y="174"/>
</points>
</Connector>
<Connector class="oracle.dbtools.crest.swingui.relational.TVFKRelation" oid="4C5D13FC-EF51-912B-5DC5-49713A2E8EDC" otype="FKIndexAssociation" vid_source="A9CBFFC9-0240-75D4-7BC9-0F00E6E23B34" vid_target="1C62262E-F54D-DD69-680A-4D768CCFDAD4">
<hideElementsInCurrentOnly>false</hideElementsInCurrentOnly>
<backgroundColor>-16777216</backgroundColor>
<lineWidth>1</lineWidth>
<points>
<point x="483" y="303"/>
<point x="483" y="590"/>
</points>
</Connector>
<Connector class="oracle.dbtools.crest.swingui.relational.TVFKRelation" oid="4F7B345E-106C-3465-240B-1020BF811CA7" otype="FKIndexAssociation" vid_source="3172480C-A348-D4F2-8F10-7057E32E7A56" vid_target="EFE05A7C-ADB9-56D5-F564-F70226A17BDF">
<hideElementsInCurrentOnly>false</hideElementsInCurrentOnly>
<backgroundColor>-16777216</backgroundColor>
<lineWidth>1</lineWidth>
<points>
<point x="943" y="497"/>
<point x="989" y="497"/>
</points>
</Connector>
<Connector class="oracle.dbtools.crest.swingui.relational.TVFKRelation" oid="51401FB9-BD7E-FF6B-DAC9-CF622D82857E" otype="FKIndexAssociation" vid_source="DB89BD44-4B50-A471-EB20-6339C2F1F1CE" vid_target="A9CBFFC9-0240-75D4-7BC9-0F00E6E23B34">
<hideElementsInCurrentOnly>false</hideElementsInCurrentOnly>
<backgroundColor>-16777216</backgroundColor>
<lineWidth>1</lineWidth>
<points>
<point x="311" y="189"/>
<point x="476" y="189"/>
</points>
</Connector>
<Connector class="oracle.dbtools.crest.swingui.relational.TVFKRelation" oid="5210DEE4-37EC-2ADE-EB37-D75BAD3E8276" otype="FKIndexAssociation" vid_source="A7FDF7EB-EFCF-1DC4-27D2-AC1DB98109E6" vid_target="A442EABB-80E2-5116-2221-8665ECDEE1BD">
<hideElementsInCurrentOnly>false</hideElementsInCurrentOnly>
<backgroundColor>-16777216</backgroundColor>
<lineWidth>1</lineWidth>
<points>
<point x="682" y="515"/>
<point x="682" y="598"/>
</points>
</Connector>
<Connector class="oracle.dbtools.crest.swingui.relational.TVFKRelation" oid="5476505E-0A3A-470C-90E3-3FF545503BB4" otype="FKIndexAssociation" vid_source="6A8A6E22-9773-23A6-1916-3218F9338106" vid_target="9C3FC4CB-3C8A-D042-76E1-44D2387CF24B">
<hideElementsInCurrentOnly>false</hideElementsInCurrentOnly>
<backgroundColor>-16777216</backgroundColor>
<lineWidth>1</lineWidth>
<points>
<point x="936" y="324"/>
<point x="512" y="670"/>
</points>
</Connector>
<Connector class="oracle.dbtools.crest.swingui.relational.TVFKRelation" oid="5D806F1B-B6BB-4257-E49C-957974955F9A" otype="FKIndexAssociation" vid_source="EFE05A7C-ADB9-56D5-F564-F70226A17BDF" vid_target="F68F75EE-A0E5-4733-0815-1E52D112980F">
<hideElementsInCurrentOnly>false</hideElementsInCurrentOnly>
<backgroundColor>-16777216</backgroundColor>
<lineWidth>1</lineWidth>
<points>
<point x="1241" y="528"/>
<point x="1341" y="528"/>
</points>
</Connector>
<Connector class="oracle.dbtools.crest.swingui.relational.TVFKRelation" oid="B20213EC-7D3C-E6EE-37EB-934F5AD88228" otype="FKIndexAssociation" vid_source="A9CBFFC9-0240-75D4-7BC9-0F00E6E23B34" vid_target="892DB848-0A51-1A36-7F03-155332A3F8BD">
<hideElementsInCurrentOnly>false</hideElementsInCurrentOnly>
<backgroundColor>-16777216</backgroundColor>
<lineWidth>1</lineWidth>
<points>
<point x="511" y="303"/>
<point x="511" y="635"/>
</points>
</Connector>
<Connector class="oracle.dbtools.crest.swingui.relational.TVFKRelation" oid="C7405E06-F04B-55E4-035B-2E796295BF1D" otype="FKIndexAssociation" vid_source="3172480C-A348-D4F2-8F10-7057E32E7A56" vid_target="A7FDF7EB-EFCF-1DC4-27D2-AC1DB98109E6">
<hideElementsInCurrentOnly>false</hideElementsInCurrentOnly>
<backgroundColor>-16777216</backgroundColor>
<lineWidth>1</lineWidth>
<points>
<point x="833" y="496"/>
<point x="780" y="496"/>
</points>
</Connector>
<Connector class="oracle.dbtools.crest.swingui.relational.TVFKRelation" oid="E1333907-3BFE-AFD3-711A-5B5C9159938B" otype="FKIndexAssociation" vid_source="A9CBFFC9-0240-75D4-7BC9-0F00E6E23B34" vid_target="9C3FC4CB-3C8A-D042-76E1-44D2387CF24B">
<hideElementsInCurrentOnly>false</hideElementsInCurrentOnly>
<backgroundColor>-16777216</backgroundColor>
<lineWidth>1</lineWidth>
<points>
<point x="488" y="303"/>
<point x="488" y="670"/>
</points>
</Connector>
<Connector class="oracle.dbtools.crest.swingui.relational.TVFKRelation" oid="E1882F8C-6D46-4AFB-DB2B-2B07B6AE1D63" otype="FKIndexAssociation" vid_source="42959AA8-2B6A-C71F-4958-CA711C14D9E1" vid_target="EFE05A7C-ADB9-56D5-F564-F70226A17BDF">
<hideElementsInCurrentOnly>false</hideElementsInCurrentOnly>
<backgroundColor>-16777216</backgroundColor>
<lineWidth>1</lineWidth>
<points>
<point x="1115" y="628"/>
<point x="1115" y="562"/>
</points>
</Connector>
<Connector class="oracle.dbtools.crest.swingui.relational.TVFKRelation" oid="E8A582DC-AEBC-3C3C-3D13-B0DBE4850904" otype="FKIndexAssociation" vid_source="EFE05A7C-ADB9-56D5-F564-F70226A17BDF" vid_target="5618833E-802B-EC56-5D2B-AF0655C7D81C">
<hideElementsInCurrentOnly>false</hideElementsInCurrentOnly>
<backgroundColor>-16777216</backgroundColor>
<lineWidth>1</lineWidth>
<points>
<point x="1062" y="417"/>
<point x="899" y="194"/>
</points>
</Connector>
<Connector class="oracle.dbtools.crest.swingui.relational.TVFKRelation" oid="E912F162-15D1-5339-7DE5-3E1BFD84B486" otype="FKIndexAssociation" vid_source="F8FE3B5D-08E0-92C7-421B-786245FFC5FE" vid_target="5618833E-802B-EC56-5D2B-AF0655C7D81C">
<hideElementsInCurrentOnly>false</hideElementsInCurrentOnly>
<backgroundColor>-16777216</backgroundColor>
<lineWidth>1</lineWidth>
<points>
<point x="1032" y="188"/>
<point x="944" y="188"/>
</points>
</Connector>
</connectors>
</Diagram>